snakeriver
