Metadata-Version: 1.0
Name: snakeriver
Version: 0.1.2
Summary: Another way to think about Hadoop Streaming in Python
Home-page: https://github.com/faithlessfriend/snakeriver
Author: Andrew Zhabinski
Author-email: faithlessfriend@gmail.com
License: MIT
Keywords: hadoop streaming
Platform: UNKNOWN
